LICENSE
README.md
setup.py
agentcoreclient/__init__.py
agentcoreclient/client.py
agentcoreclient/config.py
agentcoreclient/exceptions.py
agentcoreclient/logger.py
agentcoreclient/protocol.py
agentcoreclient/version.py
agentcoreclient.egg-info/PKG-INFO
agentcoreclient.egg-info/SOURCES.txt
agentcoreclient.egg-info/dependency_links.txt
agentcoreclient.egg-info/requires.txt
agentcoreclient.egg-info/top_level.txt