Metadata-Version: 2.1
Name: agentcoreclient
Version: 0.1.7
Summary: AgentCore Client library for building Oversight probes
Home-page: https://github.com/oversight/agentcoreclient
Author: Cesbit
Author-email: info@cesbit.com
License: UNKNOWN
Download-URL: https://github.com/oversight/agentcoreclient/tarball/v0.1.7
Keywords: parser,grammar,autocompletion
Platform: UNKNOWN
Classifier: Intended Audience :: Developers
Classifier: Operating System :: OS Independent
Classifier: Programming Language :: Python :: 3.7
Classifier: Programming Language :: Python :: 3.8
Classifier: Programming Language :: Python :: 3.9
Classifier: Programming Language :: Python :: 3.10
Classifier: Programming Language :: Python :: 3 :: Only
Classifier: Topic :: Software Development :: Libraries :: Python Modules
Classifier: Topic :: Text Processing :: Linguistic
License-File: LICENSE
